JSTimers-1.1.dist-info/METADATA
JSTimers-1.1.dist-info/RECORD
JSTimers-1.1.dist-info/WHEEL
JSTimers-1.1.dist-info/top_level.txt
jstimers/__init__.py
