Metadata-Version: 2.1
Name: JSTimers
Version: 1.1
Summary: Javascript Timer functions for Python
Home-page: https://github.com/Shashwat986/jstimers
Author: Shashwat Chandra
Author-email: chandras.2013@iitkalumni.org
License: UNKNOWN
Platform: UNKNOWN
